mpllayout/__init__.py
mpllayout/base.py
mpllayout/frame.py
mpllayout/layout.py
mpllayout/pin.py
mpllayout/ruler.py
mpllayout-0.1.3.dist-info/LICENSE
mpllayout-0.1.3.dist-info/METADATA
mpllayout-0.1.3.dist-info/WHEEL
mpllayout-0.1.3.dist-info/top_level.txt
mpllayout-0.1.3.dist-info/RECORD
