Metadata-Version: 2.1
Name: mpllayout
Version: 0.1.3
Summary: Easily create axes layouts for complex matplotlib figures.
Author: "Guangyu Li"
Author-email: Guangyu Li <gl343@cornell.edu>
License: GNU General Public License v3
Project-URL: Homepage, https://github.com/lguangyu/MatplotlibLayout.git
Project-URL: Bug Tracker, https://github.com/lguangyu/MatplotlibLayout/issues
Classifier: Programming Language :: Python :: 3
Classifier: Programming Language :: Python :: 3.7
Classifier: Programming Language :: Python :: 3.8
Classifier: Programming Language :: Python :: 3.9
Classifier: Programming Language :: Python :: 3.10
Classifier: Operating System :: OS Independent
Requires-Python: >=3.7
License-File: LICENSE
Requires-Dist: matplotlib >=3.4.0
